notificationcenter/__init__.py
notificationcenter/models.py
notificationcenter/tasks.py
notificationcenter/tests.py
notificationcenter/util.py
notificationcenter/management/__init__.py
notificationcenter/management/commands/__init__.py
notificationcenter/management/commands/send_notifications.py
notificationcenter/migrations/0001_initial.py
notificationcenter/migrations/0002_remove_notification_html_remove_notification_link_and_more.py
notificationcenter/migrations/__init__.py
django_notificationcenter-0.2.3.dist-info/METADATA
django_notificationcenter-0.2.3.dist-info/WHEEL
django_notificationcenter-0.2.3.dist-info/top_level.txt
django_notificationcenter-0.2.3.dist-info/RECORD
